markdowngiver2/__init__.py
markdowngiver2/__main__.py
markdowngiver2/server.py
superduper-0.2.0.dist-info/METADATA
superduper-0.2.0.dist-info/WHEEL
superduper-0.2.0.dist-info/top_level.txt
superduper-0.2.0.dist-info/RECORD
